{
  "javascript.suggestionActions.enabled": true,
  "javascript.inlayHints.parameterNames": "all",
  "javascript.inlayHints.variableTypes.enabled": true,
  "javascript.inlayHints.parameterTypes.enabled": true,
  "javascript.inlayHints.functionLikeReturnTypes.enabled": true,
  "javascript.autoClosingTags": true,
  "javascript.format.enable": true,
  "javascript.format.insertSpaceAfterCommaDelimiter": true,
  "javascript.format.insertSpaceAfterConstructor": true,
  "javascript.format.insertSpaceAfterFunctionKeywordForAnonymousFunctions": true,
  "javascript.format.insertSpaceAfterKeywordsInControlFlowStatements": true,
  "javascript.format.insertSpaceAfterOpeningAndBeforeClosingNonemptyParenthesis": false,
  "javascript.format.insertSpaceAfterOpeningAndBeforeClosingNonemptyBrackets": true,
  "javascript.format.insertSpaceAfterOpeningAndBeforeClosingNonemptyBraces": true,
  "javascript.format.insertSpaceAfterOpeningAndBeforeClosingEmptyBraces": true,
  "javascript.format.insertSpaceAfterOpeningAndBeforeClosingTemplateStringBraces": true,
  "javascript.format.insertSpaceAfterOpeningAndBeforeClosingJsxExpressionBraces": true,
  "javascript.format.insertSpaceAfterSemicolonInForStatements": true,
  "javascript.format.insertSpaceBeforeAndAfterBinaryOperators": true,
  "javascript.format.insertSpaceBeforeFunctionParenthesis": true,
  "javascript.format.placeOpenBraceOnNewLineForControlBlocks": false,
  "javascript.format.placeOpenBraceOnNewLineForFunctions": false,
  "javascript.format.semicolons": "insert",
  "javascript.format.quoteStyle": "double",
  "javascript.inlayHints.enumMemberValues.enabled": true,
  "javascript.inlayHints.parameterNames.enabled": "all",
  "javascript.inlayHints.propertyDeclarationTypes.enabled": true,
  "javascript.inlayHints.parameterNames.suppressWhenArgumentMatchesName": true,
  "javascript.preferences.importModuleSpecifier": "shortest",
  "javascript.preferences.importModuleSpecifierEnding": "auto",
  "javascript.preferences.jsxAttributeCompletionStyle": "auto",
  "javascript.preferences.quoteStyle": "double",
  "javascript.preferences.useAliasesForRenames": true,
  "javascript.referencesCodeLens.enabled": true,
  "javascript.suggest.completeJSDocs": true,

  "files.associations": {
    "*.js": "javascriptreact"
  },
  "editor.defaultFormatter": "esbenp.prettier-vscode",
  "editor.suggest.preview": true,
  "editor.suggest.shareSuggestSelections": true,
  "editor.suggest.showStatusBar": true,
  "editor.quickSuggestions": true,
  "editor.suggestOnTriggerCharacters": true,
  "editor.acceptSuggestionOnCommitCharacter": true,
  "editor.snippetSuggestions": "top",
  "emmet.includeLanguages": {
    "javascript": "javascriptreact"
  },
  "emmet.triggerExpansionOnTab": true,
  "emmet.showSuggestionsAsSnippets": true,
  "editor.suggest.showSnippets": true,
  "editor.formatOnSave": true,
  "workbench.iconTheme": "material-icon-theme",
  "reactSnippets.settings.prettierEnabled": true,
  "editor.tabCompletion": "onlySnippets",
  "tabnine.experimentalAutoImports": true
}
